LICENSE
README.md
setup.py
Suluoya/__init__.py
Suluoya/sly.py
Suluoya.egg-info/PKG-INFO
Suluoya.egg-info/SOURCES.txt
Suluoya.egg-info/dependency_links.txt
Suluoya.egg-info/requires.txt
Suluoya.egg-info/top_level.txt
Suluoya/app/App.py
Suluoya/app/__init__.py
Suluoya/data/Bond.py
Suluoya/data/Company.py
Suluoya/data/Date.py
Suluoya/data/Fund.py
Suluoya/data/Stock.py
Suluoya/data/__init__.py
Suluoya/log/__init__.py
Suluoya/log/log.py
Suluoya/model/__init__.py
Suluoya/model/ai.py
Suluoya/model/assess.py
Suluoya/model/pre.py
Suluoya/stock/Kline.py
Suluoya/stock/Portfolio.py
Suluoya/stock/Strategy.py
Suluoya/stock/__init__.py