Metadata-Version: 2.1
Name: Suluoya
Version: 3.4.2
Summary: A package called Suluoya.
Home-page: https://github.com/pypa/sampleproject
Author: Suluoya
Author-email: 1931960436@qq.com
Maintainer: Suluoya
Maintainer-email: 1931960436@qq.com
License: UNKNOWN
Platform: UNKNOWN
Classifier: Programming Language :: Python :: 3
Classifier: License :: OSI Approved :: MIT License
Classifier: Operating System :: OS Independent
License-File: LICENSE
